datasette_atom/__init__.py
datasette_atom-0.9.dist-info/LICENSE
datasette_atom-0.9.dist-info/METADATA
datasette_atom-0.9.dist-info/WHEEL
datasette_atom-0.9.dist-info/entry_points.txt
datasette_atom-0.9.dist-info/top_level.txt
datasette_atom-0.9.dist-info/RECORD
