Metadata-Version: 2.1
Name: datasette-atom
Version: 0.9
Summary: Datasette plugin that adds a .atom output format
Home-page: https://github.com/simonw/datasette-atom
Author: Simon Willison
License: Apache License, Version 2.0
Project-URL: Issues, https://github.com/simonw/datasette-atom/issues
Project-URL: CI, https://github.com/simonw/datasette-atom/actions
Project-URL: Changelog, https://github.com/simonw/datasette-atom/releases
License-File: LICENSE
Requires-Dist: datasette (>=0.49)
Requires-Dist: feedgen
Requires-Dist: bleach
Provides-Extra: test
Requires-Dist: pytest ; extra == 'test'
Requires-Dist: pytest-asyncio ; extra == 'test'
Requires-Dist: httpx ; extra == 'test'
